templates/LICENSE
templates/README.md
templates/__init__.py
templates/package.json
templates/build/asset-manifest.json
templates/build/favicon.ico
templates/build/index.html
templates/build/logo192.png
templates/build/logo512.png
templates/build/manifest.json
templates/build/robots.txt
templates/build/static/css/main.1e332ae8.css
templates/build/static/css/main.1e332ae8.css.map
templates/build/static/css/main.b175f5ff.css
templates/build/static/css/main.b175f5ff.css.map
templates/build/static/js/main.39ca78e7.js
templates/build/static/js/main.39ca78e7.js.LICENSE.txt
templates/build/static/js/main.39ca78e7.js.map
templates/build/static/js/main.3d4907d7.js
templates/build/static/js/main.3d4907d7.js.LICENSE.txt
templates/build/static/js/main.3d4907d7.js.map
templates/build/static/media/Entrance-slider-Slider.60b8a25960b22187735b.jpg
templates/build/static/media/MetaverseStudios-logo-original-black.893c6b061ced8d8c654a.png
templates/build/static/media/Robot_Assistant.c17d1d1616c716f77187.gif
templates/build/static/media/bathroom.6aa336aef7b7776f6e95.jpeg
templates/build/static/media/board room copy.83326dd10a2723310f2b.png
templates/build/static/media/calendarGreen.58099f18630e79f8a83a.png
templates/build/static/media/calendarPink.1a141420063b460693d5.png
templates/build/static/media/check.7a3eab5e5826751393502cd50a9f898b.svg
templates/build/static/media/default.4180c9e8df51936b2edbe886f06a542b.svg
templates/build/static/media/dropbox.217b26e4d029a2928c11.png
templates/build/static/media/expressMood.28581a4a37c6894b95b7.png
templates/build/static/media/folder.c71c2c482ab2e7e64a1e.png
templates/build/static/media/ibmmetaverseui.3c34fe16d072934a6770.jpg
templates/build/static/media/info.a1d1ee95d7cb39f53ccb599c0f0df8fb.svg
templates/build/static/media/journey copy.f90d3443a2cf69907c59.png
templates/build/static/media/link.dd2c3c4266623b8b8d4cc2e6164c4682.svg
templates/build/static/media/livingroom.b6d15ab66d4d7446d865.jpeg
withpano-1.1.8.dist-info/LICENSE
withpano-1.1.8.dist-info/METADATA
withpano-1.1.8.dist-info/WHEEL
withpano-1.1.8.dist-info/top_level.txt
withpano-1.1.8.dist-info/zip-safe
withpano-1.1.8.dist-info/RECORD
