Metadata-Version: 2.1
Name: withpano
Version: 1.1.8
Summary: WithPano build using marzipano, python and react
Home-page: UNKNOWN
Author: ARUNANGSHU HAZRA
Author-email: arun.hazra86@gmail.com
License: Licensed Materials - Property of Arunangshu Hazra © Copyright Arunangshu Hazra. 2019 All Rights Reserved.
Keywords: marzipano,panview,metamorphing,withpano
Platform: OS Independent
Classifier: Development Status :: 3 - Alpha
Classifier: Intended Audience :: Developers
Classifier: Operating System :: OS Independent
Classifier: Programming Language :: Python :: 3
Requires-Python: >=3.8
License-File: LICENSE
Requires-Dist: alembic (==1.8.1)
Requires-Dist: aniso8601 (==9.0.1)
Requires-Dist: attrs (==22.1.0)
Requires-Dist: bcrypt (==4.0.1)
Requires-Dist: bleach (==5.0.1)
Requires-Dist: certifi (==2022.9.24)
Requires-Dist: charset-normalizer (==2.1.1)
Requires-Dist: click (==8.1.3)
Requires-Dist: colorama (==0.4.5)
Requires-Dist: commonmark (==0.9.1)
Requires-Dist: dill (==0.3.5.1)
Requires-Dist: dnspython (==2.2.1)
Requires-Dist: docutils (==0.19)
Requires-Dist: ecdsa (==0.18.0)
Requires-Dist: email-validator (==1.3.0)
Requires-Dist: Flask (==2.1.3)
Requires-Dist: Flask-Bcrypt (==1.0.1)
Requires-Dist: Flask-Cache (==0.13.1)
Requires-Dist: Flask-Cors (==3.0.10)
Requires-Dist: Flask-Log-Request-ID (==0.10.1)
Requires-Dist: Flask-Login (==0.6.2)
Requires-Dist: Flask-Migrate (==3.1.0)
Requires-Dist: flask-mongoengine (==1.0.0)
Requires-Dist: flask-oidc (==1.4.0)
Requires-Dist: Flask-PyMongo (==2.3.0)
Requires-Dist: flask-restx (==0.5.1)
Requires-Dist: Flask-SQLAlchemy (==2.5.1)
Requires-Dist: Flask-WTF (==1.0.1)
Requires-Dist: greenlet (==1.1.3.post0)
Requires-Dist: httplib2 (==0.20.4)
Requires-Dist: idna (==3.4)
Requires-Dist: importlib-metadata (==5.0.0)
Requires-Dist: itsdangerous (==2.1.2)
Requires-Dist: jaraco.classes (==3.2.3)
Requires-Dist: Jinja2 (==3.1.2)
Requires-Dist: jsonschema (==4.16.0)
Requires-Dist: keyring (==23.9.3)
Requires-Dist: Mako (==1.2.3)
Requires-Dist: MarkupSafe (==2.1.1)
Requires-Dist: marshmallow (==3.18.0)
Requires-Dist: mongoengine (==0.24.2)
Requires-Dist: more-itertools (==9.0.0)
Requires-Dist: multiprocess (==0.70.13)
Requires-Dist: numpy (==1.23.4)
Requires-Dist: oauth2client (==4.1.3)
Requires-Dist: packaging (==21.3)
Requires-Dist: pandas (==1.5.0)
Requires-Dist: pkginfo (==1.8.3)
Requires-Dist: pyasn1 (==0.4.8)
Requires-Dist: pyasn1-modules (==0.2.8)
Requires-Dist: Pygments (==2.13.0)
Requires-Dist: pymongo (==4.2.0)
Requires-Dist: pyparsing (==3.0.9)
Requires-Dist: pyrsistent (==0.18.1)
Requires-Dist: python-crontab (==2.6.0)
Requires-Dist: python-dateutil (==2.8.2)
Requires-Dist: python-jose (==3.3.0)
Requires-Dist: python-keycloak (==2.6.0)
Requires-Dist: pytz (==2022.4)
Requires-Dist: pywin32-ctypes (==0.2.0)
Requires-Dist: PyYAML (==6.0)
Requires-Dist: readme-renderer (==37.2)
Requires-Dist: requests (==2.28.1)
Requires-Dist: requests-toolbelt (==0.9.1)
Requires-Dist: rfc3986 (==2.0.0)
Requires-Dist: rich (==12.6.0)
Requires-Dist: rsa (==4.9)
Requires-Dist: six (==1.16.0)
Requires-Dist: SQLAlchemy (==1.4.41)
Requires-Dist: twine (==4.0.1)
Requires-Dist: urllib3 (==1.26.12)
Requires-Dist: waitress (==2.1.2)
Requires-Dist: webencodings (==0.5.1)
Requires-Dist: websocket-client (==1.4.1)
Requires-Dist: Werkzeug (==2.1.1)
Requires-Dist: WTForms (==3.0.1)
Requires-Dist: zipp (==3.9.0)
Requires-Dist: pyjwt (==2.6.0)
Requires-Dist: termcolor (==2.0.1)
Requires-Dist: cryptography (==38.0.1)
Requires-Dist: Flask-Caching (==2.0.1)
Requires-Dist: cssutils (==2.6.0)
Requires-Dist: setuptools (==60.2.0)
Requires-Dist: beautifulsoup4 (==4.11.1)
Requires-Dist: exchangelib (==4.8.0)
Requires-Dist: camelot-py (==0.10.1)
Requires-Dist: opencv-python (==4.6.0.66)
Requires-Dist: ghostscript (==0.7)
